utility.py
dq_ai_module-1.1.0.dist-info/METADATA
dq_ai_module-1.1.0.dist-info/WHEEL
dq_ai_module-1.1.0.dist-info/top_level.txt
dq_ai_module-1.1.0.dist-info/RECORD
