Metadata-Version: 2.1
Name: dq-ai-module
Version: 1.1.0
Summary: Create data quality rules and apply them to datasets.
Author: Himanshu
Author-email: himanshu.tomar@decisionpoint.in
Classifier: Programming Language :: Python :: 3
Classifier: License :: OSI Approved :: MIT License
Classifier: Operating System :: OS Independent
Requires-Python: >=3.8
Requires-Dist: openai
